simple_saga/__init__.py
simple_saga/py.typed
simple_saga/saga/__init__.py
simple_saga/saga/base.py
simple_saga/saga/saga.py
simple_saga/saga/sync_saga.py
simple_saga/schema.py
simple_saga-0.1.3.dist-info/METADATA
simple_saga-0.1.3.dist-info/WHEEL
simple_saga-0.1.3.dist-info/licenses/LICENSE
simple_saga-0.1.3.dist-info/RECORD
