Metadata-Version: 2.4
Name: simple-saga
Version: 0.1.3
Summary: A lightweight implementation of the Saga pattern for managing distributed transactions in Python
License: MIT
License-File: LICENSE
Keywords: saga,distributed-transactions,microservices,transaction-management,arrow-kt
Author: Tetsuya Wakita
Author-email: wakita181009@gmail.com
Requires-Python: >=3.10,<4.0
Classifier: Development Status :: 3 - Alpha
Classifier: Intended Audience :: Developers
Classifier: License :: OSI Approved :: MIT License
Classifier: Programming Language :: Python :: 3
Classifier: Programming Language :: Python :: 3.10
Classifier: Programming Language :: Python :: 3.11
Classifier: Programming Language :: Python :: 3.12
Classifier: Programming Language :: Python :: 3.13
Classifier: Programming Language :: Python :: 3.14
Classifier: Topic :: Software Development :: Libraries :: Python Modules
Classifier: Typing :: Typed
